Compiled from "CountService_$$_javassist_0.java"
public class com.yaojinwei.study.proxy.advanced.CountService_$$_javassist_0 implements com.yaojinwei.study.proxy.advanced.CountService,javassist.util.proxy.ProxyObject {
  public static byte[] _filter_signature;

  public static final long serialVersionUID;

  public com.yaojinwei.study.proxy.advanced.CountService_$$_javassist_0();
    Code:
       0: aload_0
       1: getstatic     #23                 // Field javassist/util/proxy/RuntimeSupport.default_interceptor:Ljavassist/util/proxy/MethodHandler;
       4: putfield      #25                 // Field handler:Ljavassist/util/proxy/MethodHandler;
       7: aload_0
       8: invokespecial #27                 // Method java/lang/Object."<init>":()V
      11: return

  public final java.lang.Object _d0clone() throws java.lang.CloneNotSupportedException;
    Code:
       0: aload_0
       1: invokespecial #37                 // Method java/lang/Object.clone:()Ljava/lang/Object;
       4: areturn

  protected final java.lang.Object clone() throws java.lang.CloneNotSupportedException;
    Code:
       0: getstatic     #41                 // Field _methods_:[Ljava/lang/reflect/Method;
       3: astore_1
       4: aload_0
       5: ldc           #42                 // String clone
       7: ldc           #43                 // String _d0clone
       9: iconst_0
      10: ldc           #44                 // String ()Ljava/lang/Object;
      12: aload_1
      13: invokestatic  #48                 // Method javassist/util/proxy/RuntimeSupport.find2Methods:(Ljava/lang/Object;Ljava/lang/String;Ljava/lang/String;ILjava/lang/String;[Ljava/lang/reflect/Method;)V
      16: aload_0
      17: getfield      #50                 // Field handler:Ljavassist/util/proxy/MethodHandler;
      20: aload_0
      21: aload_1
      22: iconst_0
      23: aaload
      24: aload_1
      25: iconst_1
      26: aaload
      27: iconst_0
      28: anewarray     #51                 // class java/lang/Object
      31: invokeinterface #57,  5           // InterfaceMethod javassist/util/proxy/MethodHandler.invoke:(Ljava/lang/Object;Ljava/lang/reflect/Method;Ljava/lang/reflect/Method;[Ljava/lang/Object;)Ljava/lang/Object;
      36: checkcast     #4                  // class java/lang/Object
      39: areturn

  public final int count();
    Code:
       0: getstatic     #61                 // Field _methods_:[Ljava/lang/reflect/Method;
       3: astore_1
       4: aload_0
       5: ldc           #62                 // String count
       7: aconst_null
       8: iconst_2
       9: ldc           #63                 // String ()I
      11: aload_1
      12: invokestatic  #48                 // Method javassist/util/proxy/RuntimeSupport.find2Methods:(Ljava/lang/Object;Ljava/lang/String;Ljava/lang/String;ILjava/lang/String;[Ljava/lang/reflect/Method;)V
      15: aload_0
      16: getfield      #64                 // Field handler:Ljavassist/util/proxy/MethodHandler;
      19: aload_0
      20: aload_1
      21: iconst_2
      22: aaload
      23: aload_1
      24: iconst_3
      25: aaload
      26: iconst_0
      27: anewarray     #51                 // class java/lang/Object
      30: invokeinterface #57,  5           // InterfaceMethod javassist/util/proxy/MethodHandler.invoke:(Ljava/lang/Object;Ljava/lang/reflect/Method;Ljava/lang/reflect/Method;[Ljava/lang/Object;)Ljava/lang/Object;
      35: checkcast     #66                 // class java/lang/Integer
      38: invokevirtual #69                 // Method java/lang/Integer.intValue:()I
      41: ireturn

  public final boolean _d2equals(java.lang.Object);
    Code:
       0: aload_0
       1: aload_1
       2: invokespecial #74                 // Method java/lang/Object.equals:(Ljava/lang/Object;)Z
       5: ireturn

  public final boolean equals(java.lang.Object);
    Code:
       0: getstatic     #76                 // Field _methods_:[Ljava/lang/reflect/Method;
       3: astore_2
       4: aload_0
       5: ldc           #77                 // String equals
       7: ldc           #78                 // String _d2equals
       9: iconst_4
      10: ldc           #79                 // String (Ljava/lang/Object;)Z
      12: aload_2
      13: invokestatic  #48                 // Method javassist/util/proxy/RuntimeSupport.find2Methods:(Ljava/lang/Object;Ljava/lang/String;Ljava/lang/String;ILjava/lang/String;[Ljava/lang/reflect/Method;)V
      16: aload_0
      17: getfield      #80                 // Field handler:Ljavassist/util/proxy/MethodHandler;
      20: aload_0
      21: aload_2
      22: iconst_4
      23: aaload
      24: aload_2
      25: iconst_5
      26: aaload
      27: iconst_1
      28: anewarray     #51                 // class java/lang/Object
      31: dup
      32: iconst_0
      33: aload_1
      34: aastore
      35: invokeinterface #57,  5           // InterfaceMethod javassist/util/proxy/MethodHandler.invoke:(Ljava/lang/Object;Ljava/lang/reflect/Method;Ljava/lang/reflect/Method;[Ljava/lang/Object;)Ljava/lang/Object;
      40: checkcast     #82                 // class java/lang/Boolean
      43: invokevirtual #86                 // Method java/lang/Boolean.booleanValue:()Z
      46: ireturn

  public final void _d3finalize() throws java.lang.Throwable;
    Code:
       0: aload_0
       1: invokespecial #92                 // Method java/lang/Object.finalize:()V
       4: return

  protected final void finalize() throws java.lang.Throwable;
    Code:
       0: getstatic     #94                 // Field _methods_:[Ljava/lang/reflect/Method;
       3: astore_1
       4: aload_0
       5: ldc           #95                 // String finalize
       7: ldc           #96                 // String _d3finalize
       9: bipush        6
      11: ldc           #97                 // String ()V
      13: aload_1
      14: invokestatic  #48                 // Method javassist/util/proxy/RuntimeSupport.find2Methods:(Ljava/lang/Object;Ljava/lang/String;Ljava/lang/String;ILjava/lang/String;[Ljava/lang/reflect/Method;)V
      17: aload_0
      18: getfield      #98                 // Field handler:Ljavassist/util/proxy/MethodHandler;
      21: aload_0
      22: aload_1
      23: bipush        6
      25: aaload
      26: aload_1
      27: bipush        7
      29: aaload
      30: iconst_0
      31: anewarray     #51                 // class java/lang/Object
      34: invokeinterface #57,  5           // InterfaceMethod javassist/util/proxy/MethodHandler.invoke:(Ljava/lang/Object;Ljava/lang/reflect/Method;Ljava/lang/reflect/Method;[Ljava/lang/Object;)Ljava/lang/Object;
      39: pop
      40: return

  public final int _d5hashCode();
    Code:
       0: aload_0
       1: invokespecial #102                // Method java/lang/Object.hashCode:()I
       4: ireturn

  public final int hashCode();
    Code:
       0: getstatic     #104                // Field _methods_:[Ljava/lang/reflect/Method;
       3: astore_1
       4: aload_0
       5: ldc           #105                // String hashCode
       7: ldc           #106                // String _d5hashCode
       9: bipush        10
      11: ldc           #107                // String ()I
      13: aload_1
      14: invokestatic  #48                 // Method javassist/util/proxy/RuntimeSupport.find2Methods:(Ljava/lang/Object;Ljava/lang/String;Ljava/lang/String;ILjava/lang/String;[Ljava/lang/reflect/Method;)V
      17: aload_0
      18: getfield      #108                // Field handler:Ljavassist/util/proxy/MethodHandler;
      21: aload_0
      22: aload_1
      23: bipush        10
      25: aaload
      26: aload_1
      27: bipush        11
      29: aaload
      30: iconst_0
      31: anewarray     #51                 // class java/lang/Object
      34: invokeinterface #110,  5          // InterfaceMethod javassist/util/proxy/MethodHandler.invoke:(Ljava/lang/Object;Ljava/lang/reflect/Method;Ljava/lang/reflect/Method;[Ljava/lang/Object;)Ljava/lang/Object;
      39: checkcast     #66                 // class java/lang/Integer
      42: invokevirtual #69                 // Method java/lang/Integer.intValue:()I
      45: ireturn

  public final java.lang.String _d8toString();
    Code:
       0: aload_0
       1: invokespecial #115                // Method java/lang/Object.toString:()Ljava/lang/String;
       4: areturn

  public final java.lang.String toString();
    Code:
       0: getstatic     #117                // Field _methods_:[Ljava/lang/reflect/Method;
       3: astore_1
       4: aload_0
       5: ldc           #118                // String toString
       7: ldc           #119                // String _d8toString
       9: bipush        16
      11: ldc           #120                // String ()Ljava/lang/String;
      13: aload_1
      14: invokestatic  #48                 // Method javassist/util/proxy/RuntimeSupport.find2Methods:(Ljava/lang/Object;Ljava/lang/String;Ljava/lang/String;ILjava/lang/String;[Ljava/lang/reflect/Method;)V
      17: aload_0
      18: getfield      #122                // Field handler:Ljavassist/util/proxy/MethodHandler;
      21: aload_0
      22: aload_1
      23: bipush        16
      25: aaload
      26: aload_1
      27: bipush        17
      29: aaload
      30: iconst_0
      31: anewarray     #51                 // class java/lang/Object
      34: invokeinterface #124,  5          // InterfaceMethod javassist/util/proxy/MethodHandler.invoke:(Ljava/lang/Object;Ljava/lang/reflect/Method;Ljava/lang/reflect/Method;[Ljava/lang/Object;)Ljava/lang/Object;
      39: checkcast     #126                // class java/lang/String
      42: areturn

  static {};
    Code:
       0: bipush        24
       2: anewarray     #129                // class java/lang/reflect/Method
       5: putstatic     #130                // Field _methods_:[Ljava/lang/reflect/Method;
       8: ldc2_w        #131                // long -1l
      11: putstatic     #134                // Field serialVersionUID:J
      14: return

  public void setHandler(javassist.util.proxy.MethodHandler);
    Code:
       0: aload_0
       1: aload_1
       2: putfield      #122                // Field handler:Ljavassist/util/proxy/MethodHandler;
       5: return

  public javassist.util.proxy.MethodHandler getHandler();
    Code:
       0: aload_0
       1: getfield      #122                // Field handler:Ljavassist/util/proxy/MethodHandler;
       4: areturn

  java.lang.Object writeReplace() throws java.io.ObjectStreamException;
    Code:
       0: aload_0
       1: invokestatic  #145                // Method javassist/util/proxy/RuntimeSupport.makeSerializedProxy:(Ljava/lang/Object;)Ljavassist/util/proxy/SerializedProxy;
       4: areturn
}
